.dada-version
MANIFEST.in
README.md
requirements.txt
setup.cfg
setup.py
dada_http/__init__.py
dada_http.egg-info/PKG-INFO
dada_http.egg-info/SOURCES.txt
dada_http.egg-info/dependency_links.txt
dada_http.egg-info/requires.txt
dada_http.egg-info/top_level.txt
dada_http/tests/__init__.py
dada_http/tests/test_http.py